{"we:need": {"your": 1, "to": 1}, "need:your": {"voice": 1, "help": 3}, "your:voice": {"as": 1, "in": 1}, "voice:as": {"we": 1}, "as:we": {"continue": 1}, "we:continue": {"the": 1, "to": 1}, "continue:the": {"fight": 1}, "the:fight": {"for": 2}, "fight:for": {"net": 1, "the": 1, "an": 1}, "for:net": {"neutrality": 3}, "an:open": {"letter": 1, "and": 1, "internet": 1}, "open:letter": {"to": 1}, "letter:to": {"the": 1}, "to:the": {"reddit": 2, "dozen": 1, "insert": 1, "sorcerers": 1}, "the:reddit": {"community": 3, "internship": 1, "gifts": 1, "stream": 1, "alien": 1, "snoo": 1, "postcards": 1}, "an:update": {"on": 3}, "update:on": {"the": 3, "what": 1, "some": 1, "gold": 1}, "on:the": {"fight": 1, "internet": 1, "recent": 1, "watching": 1, "colbertstewart": 1, "metaphor": 1, "future": 1, "grow": 1}, "for:the": {"free": 1, "internet": 2, "teachers": 4, "largest": 1, "extra": 1, "holidays": 1, "summer": 1, "gold": 1, "count": 1, "annual": 1, "best": 4, "troops": 1}, "the:free": {"and": 1, "software": 1}, "free:and": {"open": 1}, "and:open": {"internet": 1}, "the:battle": {"for": 1}, "battle:for": {"the": 1}, "the:internet": {"is": 1, "slowdown": 1, "just": 1}, "internet:is": {"now": 1}, "is:now": {"join": 1, "open": 1, "up": 1}, "now:join": {"us": 1}, "join:us": {"for": 3, "in": 2, "on": 2, "once": 1, "before": 1, "november": 1, "to": 1, "each": 1}, "us:for": {"the": 1, "our": 2}, "internet:slowdown": {"and": 1}, "slowdown:and": {"tell": 1}, "and:tell": {"congress": 1}, "tell:congress": {"to": 1}, "congress:to": {"support": 1}, "to:support": {"an": 1, "secret": 1}, "support:an": {"open": 1}, "open:and": {"neutral": 1}, "and:neutral": {"internet": 1}, "reddit:is": {"filing": 1, "fcc": 1, "top": 1, "privacy": 1, "official": 1, "creative": 1, "best": 4, "livestream": 2, "backup": 1, "help": 1, "hiring": 3, "doubling": 1}, "is:filing": {"an": 1}, "filing:an": {"fcc": 1}, "an:fcc": {"comment": 1}, "fcc:comment": {"to": 1}, "comment:to": {"fight": 1}, "to:fight": {"for": 1}, "for:an": {"open": 1}, "open:internet": {"we": 1}, "internet:we": {"want": 1}, "we:want": {"your": 2}, "want:your": {"voice": 1, "feedback": 1}, "voice:in": {"it": 1}, "in:it": {"as": 1}, "it:as": {"well": 1}, "an:analysis": {"of": 1}, "analysis:of": {"net": 1}, "of:net": {"neutrality": 1}, "net:neutrality": {"activism": 1, "it": 1, "at": 1}, "neutrality:activism": {"on": 1}, "activism:on": {"reddit": 1}, "looking:back": {"at": 1}, "back:at": {"rplace": 1}, "us:in": {"a": 1, "helping": 1}, "in:a": {"final": 1, "reddit": 2}, "a:final": {"push": 1}, "final:push": {"for": 1}, "push:for": {"net": 1}, "neutrality:it": {"is": 1}, "it:is": {"as": 1, "about": 2, "time": 6, "cold": 1, "that": 2, "almost": 1}, "is:as": {"easy": 1}, "as:easy": {"as": 1}, "easy:as": {"calling": 1}, "as:calling": {"wheeler": 1}, "thank:you": {"to": 1, "reddit": 1, "internet": 1}, "you:to": {"the": 1, "choose": 1}, "the:dozen": {"dc": 1}, "dozen:dc": {"redditors": 1}, "dc:redditors": {"who": 1}, "redditors:who": {"braved": 1}, "who:braved": {"pouring": 1}, "braved:pouring": {"rain": 1}, "pouring:rain": {"to": 1}, "rain:to": {"handdeliver": 1}, "to:handdeliver": {"reddit": 1}, "handdeliver:reddit": {"is": 1}, "is:fcc": {"comments": 1}, "fun:is": {"not": 1}, "is:not": {"something": 1, "too": 2}, "not:something": {"one": 1}, "something:one": {"considers": 1}, "one:considers": {"when": 1}, "considers:when": {"banning": 1}, "when:banning": {"half": 1}, "banning:half": {"a": 1}, "half:a": {"subreddit": 1}, "calling:all": {"redditors": 1, "local": 1}, "all:redditors": {"to": 1}, "redditors:to": {"help": 1}, "to:help": {"nepal": 2, "support": 1}, "help:nepal": {"earthquake": 1, "and": 1}, "nepal:earthquake": {"victims": 1}, "the:button": {"has": 1}, "button:has": {"ended": 1}, "announcing:the": {"reddit": 1, "official": 1, "winners": 1, "tshirt": 1}, "reddit:internship": {"for": 1}, "internship:for": {"engineers": 1}, "for:engineers": {"rife": 1}, "join:a": {"reddit": 3, "tradition": 2, "yearly": 1}, "a:reddit": {"tradition": 5, "podcast": 1}, "reddit:tradition": {"in": 3, "our": 1, "now": 1}, "tradition:in": {"its": 3}, "in:its": {"straight": 3}, "its:straight": {"santa": 1, "year": 2}, "straight:santa": {"is": 1}, "santa:is": {"now": 1, "is": 1, "open": 1}, "now:open": {"currently": 1}, "open:currently": {"over": 1}, "currently:over": {"redditors": 1}, "over:redditors": {"signed": 1, "from": 1}, "redditors:signed": {"up": 1}, "signed:up": {"in": 1, "who": 1}, "up:in": {"hours": 1}, "let:s": {"help": 1, "get": 2}, "s:help": {"teachers": 1}, "help:teachers": {"get": 2, "with": 1}, "teachers:get": {"the": 2}, "get:the": {"supplies": 2}, "the:supplies": {"they": 2}, "supplies:they": {"desperately": 1, "so": 1}, "they:desperately": {"need": 1}, "desperately:need": {"join": 2}, "need:join": {"us": 2}, "for:our": {"fourth": 1, "third": 1}, "our:fourth": {"annual": 1}, "fourth:annual": {"reddit": 1}, "annual:reddit": {"gifts": 3, "close": 1}, "reddit:gifts": {"for": 4, "secret": 2, "arbitrary": 1, "summer": 1}, "gifts:for": {"the": 4}, "nearly:redditors": {"from": 2}, "redditors:from": {"around": 1, "countries": 2}, "from:around": {"the": 1}, "around:the": {"world": 3}, "the:world": {"have": 1, "make": 1, "spin": 1, "is": 2, "will": 1}, "world:have": {"joined": 1}, "have:joined": {"reddit": 1, "this": 2}, "joined:reddit": {"gifts": 1}, "gifts:secret": {"santa": 2}, "secret:santa": {"do": 3, "signups": 5, "gift": 1, "is": 2, "back": 1, "now": 2, "program": 1, "sign": 1, "was": 1, "more": 1}, "santa:do": {"not": 3}, "do:not": {"miss": 3}, "not:miss": {"out": 1, "outonly": 2}, "miss:out": {"on": 1}, "out:on": {"an": 1}, "on:an": {"annual": 1, "unrelated": 1}, "an:annual": {"reddit": 1}, "reddit:close": {"in": 1}, "close:in": {"week": 1}, "hell:it": {"is": 1}, "is:about": {"time": 2}, "about:time": {"reddit": 1, "we": 1}, "time:reddit": {"now": 1}, "reddit:now": {"supports": 1, "holds": 1, "available": 1}, "now:supports": {"fullsite": 1}, "supports:fullsite": {"https": 1}, "reddit:s": {"first": 1, "appearance": 1, "year": 1, "internship": 1, "communities": 1}, "s:first": {"transparency": 1}, "first:transparency": {"report": 1}, "the:alien": {"has": 1}, "alien:has": {"landed": 1}, "straight:year": {"secret": 2}, "year:secret": {"santa": 2}, "santa:signups": {"are": 5}, "signups:are": {"now": 3, "open": 4}, "are:now": {"open": 3}, "time:to": {"call": 1, "invest": 1, "do": 1, "choose": 1}, "to:call": {"the": 1}, "call:the": {"fcc": 1}, "the:fcc": {"we": 1}, "fcc:we": {"are": 1}, "we:are": {"nearing": 1, "here": 1, "going": 1, "crossing": 1, "too": 1, "thankful": 1, "sharing": 1}, "are:nearing": {"the": 1}, "nearing:the": {"home": 1}, "the:home": {"stretch": 1}, "home:stretch": {"for": 1}, "stretch:for": {"net": 1}, "neutrality:at": {"the": 1}, "at:the": {"fcc": 1, "pretty": 1}, "we:did": {"it": 2, "an": 1}, "did:it": {"again": 1, "we": 1}, "it:again": {"guinness": 1, "with": 1}, "again:guinness": {"world": 1}, "guinness:world": {"record": 5, "s": 1}, "world:record": {"holders": 1, "reddit": 1, "in": 1, "setting": 1}, "record:holders": {"for": 1}, "holders:for": {"the": 1}, "the:largest": {"secret": 1}, "largest:secret": {"santa": 2}, "santa:gift": {"exchange": 1}, "reddit:donate": {"of": 1}, "donate:of": {"our": 1}, "of:our": {"advertising": 1, "own": 1, "recent": 1}, "our:advertising": {"revenue": 1}, "advertising:revenue": {"will": 1}, "revenue:will": {"be": 1}, "will:be": {"donated": 1, "this": 1, "down": 1}, "be:donated": {"to": 1}, "donated:to": {"charities": 1}, "to:charities": {"you": 1}, "charities:you": {"choose": 1}, "you:choose": {"voting": 1}, "choose:voting": {"begins": 1}, "voting:begins": {"now": 1}, "extra:life": {"is": 4, "the": 1, "help": 2, "game": 2, "gaming": 3, "reddit": 1, "come": 1}, "life:is": {"almost": 3, "coming": 1}, "is:almost": {"here": 3, "halloween": 1}, "almost:here": {"join": 3}, "here:join": {"team": 1, "us": 2}, "join:team": {"reddit": 3}, "team:reddit": {"on": 1, "for": 2, "would": 1}, "reddit:on": {"nov": 1}, "on:nov": {"to": 1}, "nov:to": {"raise": 1}, "to:raise": {"money": 1, "a": 1}, "raise:money": {"for": 4}, "money:for": {"children": 5}, "for:children": {"s": 2, "is": 3}, "children:s": {"hospitals": 3}, "from:countries": {"have": 2}, "countries:have": {"joined": 2, "the": 1}, "joined:this": {"year": 2}, "this:year": {"is": 2, "with": 1}, "year:is": {"secret": 2, "resolutions": 2}, "is:secret": {"santa": 2}, "miss:outonly": {"week": 2}, "outonly:week": {"left": 2}, "week:left": {"to": 2}, "left:to": {"sign": 2}, "to:sign": {"up": 2}, "announcing:an": {"entirely": 1}, "an:entirely": {"new": 1}, "entirely:new": {"part": 1}, "new:part": {"of": 1}, "part:of": {"reddit": 1}, "of:reddit": {"we": 1, "donate": 1, "reintroducing": 1, "explore": 1, "mobile": 1, "mold": 1, "s": 2, "awards": 2}, "reddit:we": {"hope": 1, "have": 1, "need": 1}, "we:hope": {"you": 1}, "hope:you": {"ll": 1}, "you:ll": {"love": 1}, "ll:love": {"redditmade": 1}, "happy:birthday": {"to": 1}, "birthday:to": {"us": 1}, "to:us": {"celebrating": 1}, "us:celebrating": {"the": 1}, "celebrating:the": {"best": 1}, "the:best": {"of": 9, "reddit": 1, "discounts": 1, "community": 1}, "best:of": {"years": 1, "secret": 1, "awards": 4, "reddit": 5, "winners": 1}, "of:years": {"of": 1}, "years:of": {"reddit": 1}, "bring:us": {"your": 1}, "us:your": {"tired": 1}, "your:tired": {"your": 1}, "tired:your": {"weak": 1}, "your:weak": {"your": 1}, "weak:your": {"jobseekers": 1}, "announcing:upvoted": {"weekly": 1}, "upvoted:weekly": {"a": 1}, "weekly:a": {"new": 1}, "a:new": {"optin": 1, "guinness": 1, "motto": 1, "global": 1}, "new:optin": {"way": 1}, "optin:way": {"to": 1}, "way:to": {"enjoy": 1, "browse": 1}, "to:enjoy": {"the": 1}, "enjoy:the": {"best": 1}, "best:reddit": {"content": 1}, "reddit:content": {"you": 1}, "content:you": {"may": 1}, "you:may": {"have": 1}, "may:have": {"missed": 1}, "have:missed": {"during": 1}, "missed:during": {"the": 1}, "during:the": {"week": 1}, "they:so": {"desperately": 1}, "so:desperately": {"need": 1}, "our:third": {"annual": 1}, "third:annual": {"reddit": 1}, "upvoted:a": {"reddit": 1, "redditorial": 1}, "reddit:podcast": {"for": 1}, "podcast:for": {"all": 1}, "for:all": {"the": 2}, "all:the": {"stories": 1, "postcards": 1}, "the:stories": {"behind": 1, "that": 1}, "stories:behind": {"the": 1}, "behind:the": {"stories": 1}, "stories:that": {"hit": 1}, "that:hit": {"our": 1}, "hit:our": {"frontpages": 1}, "are:open": {"join": 1}, "open:join": {"a": 1}, "a:tradition": {"help": 1, "break": 1}, "tradition:help": {"break": 1}, "help:break": {"a": 1, "the": 1}, "break:a": {"world": 2}, "a:world": {"record": 4}, "participate:in": {"a": 2, "the": 1}, "tradition:our": {"eighth": 1}, "our:eighth": {"annual": 1}, "eighth:annual": {"summer": 1}, "annual:summer": {"secret": 1}, "summer:secret": {"santa": 3}, "is:is": {"the": 1}, "is:the": {"reddit": 1, "time": 1, "final": 1}, "gifts:arbitrary": {"day": 1}, "arbitrary:day": {"exchange": 1, "is": 1, "signups": 2, "global": 1}, "hey:we": {"are": 1}, "are:here": {"to": 1}, "here:to": {"talk": 1}, "to:talk": {"about": 1}, "talk:about": {"that": 1}, "about:that": {"desktop": 1}, "that:desktop": {"redesign": 1}, "desktop:redesign": {"you": 1}, "redesign:you": {"are": 1}, "you:are": {"all": 1, "a": 1, "busy": 1}, "are:all": {"so": 1}, "all:so": {"excited": 1}, "so:excited": {"about": 1}, "reddit:for": {"extra": 2, "free": 1}, "for:extra": {"life": 4}, "life:the": {"gaming": 1}, "the:gaming": {"marathon": 1}, "gaming:marathon": {"benefiting": 1, "raising": 1}, "marathon:benefiting": {"children": 1}, "benefiting:children": {"is": 2}, "children:is": {"hospitals": 4, "miracle": 1}, "so:long": {"and": 1}, "long:and": {"thanks": 1}, "and:thanks": {"for": 1}, "thanks:for": {"all": 1, "the": 1}, "global:reddit": {"meetup": 16, "service": 3}, "reddit:meetup": {"day": 19, "at": 1}, "meetup:day": {"is": 9, "one": 1, "v": 2, "iii": 1, "will": 1, "on": 1, "decorate": 1, "and": 1, "update": 1}, "day:is": {"coming": 3, "june": 1, "here": 2, "this": 2, "saturday": 1, "on": 1, "upon": 1, "happening": 1}, "is:coming": {"set": 2, "join": 1, "up": 1}, "coming:set": {"your": 2}, "set:your": {"calendars": 2}, "your:calendars": {"for": 2}, "calendars:for": {"june": 2}, "announcing:reddit": {"live": 1, "notes": 1, "companion": 1}, "announcing:embeddable": {"comment": 1}, "embeddable:comment": {"threads": 1}, "the:official": {"reddit": 1}, "official:reddit": {"ama": 1}, "reddit:ama": {"app": 1}, "the:winners": {"of": 1, "in": 2}, "winners:of": {"reddit": 1, "the": 1}, "life:help": {"kids": 1, "us": 1}, "help:kids": {"and": 1}, "kids:and": {"play": 1}, "and:play": {"games": 1}, "play:games": {"benefiting": 1, "and": 3}, "games:benefiting": {"children": 1}, "is:miracle": {"network": 1}, "miracle:network": {"hospitals": 1}, "help:us": {"make": 1, "raise": 2, "design": 1, "support": 1}, "us:make": {"reddit": 1}, "make:reddit": {"better": 1}, "reddit:better": {"by": 1}, "better:by": {"taking": 1}, "by:taking": {"this": 1}, "taking:this": {"survey": 1}, "teachers:really": {"need": 1}, "really:need": {"your": 2}, "your:help": {"reddit": 1}, "is:time": {"for": 5, "to": 1}, "time:for": {"extra": 2, "us": 1, "you": 1, "qr": 1}, "us:raise": {"money": 2}, "is:hospitals": {"and": 2}, "hospitals:and": {"watch": 2}, "and:watch": {"reddit": 1, "the": 1}, "watch:reddit": {"stream": 1, "is": 1}, "reddit:stream": {"live": 2}, "stream:live": {"on": 2}, "live:on": {"twitch": 2}, "on:twitch": {"now": 2}, "of:secret": {"santa": 1}, "is:june": {"together": 1}, "june:together": {"we": 1}, "together:we": {"re": 1}, "we:re": {"better": 1, "back": 1, "fighting": 1}, "dear:reddit": {"we": 1, "it": 1}, "we:have": {"a": 1, "rewritten": 1, "one": 1, "some": 1}, "have:a": {"lot": 1, "runoff": 1}, "a:lot": {"of": 1}, "lot:of": {"teachers": 1}, "of:teachers": {"signed": 1}, "teachers:signed": {"up": 1}, "up:who": {"really": 1}, "who:really": {"need": 1}, "how:reddit": {"works": 2}, "remember:the": {"human": 1}, "life:game": {"day": 2}, "game:day": {"is": 1}, "is:here": {"help": 1, "again": 1}, "here:help": {"us": 1}, "watch:the": {"reddit": 1}, "the:eu": {"copyright": 1}, "eu:copyright": {"directive": 1}, "copyright:directive": {"what": 1}, "directive:what": {"redditors": 1}, "what:redditors": {"in": 1}, "redditors:in": {"europe": 1, "over": 1}, "in:europe": {"need": 1}, "europe:need": {"to": 1}, "need:to": {"know": 2, "talk": 1}, "on:what": {"the": 1}, "what:the": {"reddit": 1}, "reddit:community": {"has": 1}, "community:has": {"done": 1}, "has:done": {"so": 1}, "done:so": {"far": 1}, "so:far": {"to": 1}, "far:to": {"help": 1}, "nepal:and": {"what": 1}, "and:what": {"is": 1}, "what:is": {"still": 1, "that": 1, "in": 1, "snoo": 1, "hooded": 1}, "is:still": {"needed": 1}, "only:you": {"can": 1}, "you:can": {"protect": 1}, "can:protect": {"net": 1}, "protect:net": {"neutrality": 1}, "a:personal": {"message": 1, "note": 1}, "personal:message": {"from": 1}, "message:from": {"stephen": 1}, "from:stephen": {"colbert": 1}, "stephen:colbert": {"to": 1, "interview": 1}, "colbert:to": {"the": 1}, "us:on": {"november": 2}, "on:november": {"to": 2}, "november:to": {"help": 1, "play": 1}, "help:support": {"children": 1, "classrooms": 1}, "support:children": {"s": 1}, "is:this": {"saturday": 2}, "this:saturday": {"june": 3, "september": 1}, "saturday:june": {"find": 3}, "june:find": {"or": 2, "a": 1}, "find:or": {"organize": 2}, "or:organize": {"an": 2}, "organize:an": {"event": 2}, "an:event": {"in": 2}, "event:in": {"your": 2}, "in:your": {"is": 2}, "your:is": {"not": 2}, "not:too": {"late": 2}, "too:late": {"full": 2, "play": 1}, "late:full": {"list": 2}, "full:list": {"inside": 1, "plus": 1}, "the:teachers": {"has": 1}, "teachers:has": {"arrived": 1}, "has:arrived": {"in": 1}, "arrived:in": {"partnership": 1}, "in:partnership": {"with": 1}, "partnership:with": {"our": 1}, "with:our": {"friends": 1}, "our:friends": {"at": 1}, "friends:at": {"donorschooseorg": 1}, "at:donorschooseorg": {"will": 1}, "donorschooseorg:will": {"you": 1}, "will:you": {"help": 2, "come": 1}, "you:help": {"support": 1, "us": 1}, "support:classrooms": {"for": 1}, "classrooms:for": {"thousands": 1}, "for:thousands": {"of": 1}, "thousands:of": {"students": 1}, "of:students": {"and": 1}, "students:and": {"teachers": 1}, "and:teachers": {"this": 1}, "teachers:this": {"year": 1}, "stopped:they": {"must": 1}, "they:must": {"be": 1}, "must:be": {"on": 1}, "be:on": {"this": 1}, "on:this": {"all": 1}, "this:all": {"depends": 1}, "happy:holidays": {"from": 3, "you": 2}, "holidays:from": {"all": 3}, "from:all": {"of": 4}, "all:of": {"us": 4}, "of:us": {"at": 4}, "us:at": {"reddit": 4, "pycon": 1}, "change:reddit": {"s": 1}, "s:appearance": {"with": 1}, "appearance:with": {"reddit": 1}, "with:reddit": {"themes": 1, "gold": 1, "is": 1}, "reddit:themes": {"other": 1}, "themes:other": {"new": 1}, "other:new": {"gold": 1}, "new:gold": {"benefits": 1, "payment": 1}, "us:once": {"again": 1}, "once:again": {"for": 1}, "again:for": {"the": 1}, "the:extra": {"life": 1}, "life:gaming": {"marathon": 3}, "marathon:raising": {"money": 1}, "raising:money": {"for": 1}, "is:top": {"saved": 1, "debating": 1}, "top:saved": {"comments": 1}, "saved:comments": {"posts": 1}, "create:your": {"own": 1}, "your:own": {"reddit": 1, "collections": 1}, "own:reddit": {"alien": 1}, "reddit:alien": {"avatar": 1, "on": 1}, "alien:avatar": {"with": 1}, "avatar:with": {"reddit": 1}, "today:we": {"fight": 1}, "we:fight": {"back": 1}, "fight:back": {"against": 1}, "back:against": {"mass": 1}, "against:mass": {"surveillance": 1}, "a:technical": {"examination": 1}, "technical:examination": {"of": 1}, "examination:of": {"sopa": 1}, "of:sopa": {"and": 1}, "sopa:and": {"protect": 1}, "and:protect": {"ip": 1}, "a:yearly": {"reddit": 1}, "yearly:reddit": {"tradition": 1}, "tradition:now": {"celebrating": 1}, "now:celebrating": {"our": 1}, "celebrating:our": {"annual": 1}, "our:annual": {"holiday": 2, "reddit": 1}, "annual:holiday": {"event": 1, "greeting": 1}, "holiday:event": {"reddit": 1}, "event:reddit": {"gifts": 1}, "update:in": {"less": 1}, "in:less": {"than": 1}, "less:than": {"eight": 1, "two": 1}, "than:eight": {"hours": 1}, "eight:hours": {"the": 1}, "hours:the": {"colbertrally": 1}, "the:colbertrally": {"movement": 1}, "colbertrally:movement": {"has": 1}, "movement:has": {"completely": 1}, "has:completely": {"obliterated": 1}, "completely:obliterated": {"hillary": 1}, "obliterated:hillary": {"clinton": 1}, "hillary:clinton": {"is": 1}, "clinton:is": {"record": 1}, "is:record": {"and": 1}, "record:and": {"the": 1}, "and:the": {"charity": 1, "best": 1, "missus": 1, "servers": 1, "reddit": 1, "subreddits": 1}, "the:charity": {"is": 1}, "charity:is": {"tallying": 1}, "is:tallying": {"server": 1}, "dear:entire": {"mainstream": 1}, "entire:mainstream": {"media": 1}, "mainstream:media": {"please": 1}, "media:please": {"stop": 1}, "please:stop": {"referring": 1}, "stop:referring": {"to": 1}, "referring:to": {"reddit": 1}, "to:reddit": {"as": 1, "is": 1, "gold": 1}, "reddit:as": {"small": 1}, "as:small": {"the": 1}, "small:the": {"team": 1, "site": 1}, "the:team": {"may": 1}, "team:may": {"be": 1}, "may:be": {"small": 1}, "be:small": {"the": 1}, "the:site": {"is": 1}, "site:is": {"anything": 1}, "is:anything": {"but": 1}, "a:snoo": {"like": 1}, "snoo:like": {"you": 1}, "s:year": {"in": 1}, "year:in": {"review": 1}, "i:will": {"take": 1, "name": 1, "hug": 1}, "will:take": {"one": 1}, "take:one": {"hygge": 1}, "one:hygge": {"please": 1}, "reddit:myth": {"busters": 1}, "browse:the": {"future": 1}, "the:future": {"of": 3}, "future:of": {"reddit": 1, "fundraising": 1, "news": 1}, "reddit:reintroducing": {"multireddits": 1}, "finders:keepers": {"losers": 1}, "keepers:losers": {"weepers": 1}, "losers:weepers": {"the": 1}, "weepers:the": {"hunt": 1}, "the:hunt": {"starts": 1}, "hunt:starts": {"now": 1}, "helping:haiti": {"because": 1}, "haiti:because": {"we": 1}, "because:we": {"ought": 1}, "we:ought": {"to": 1}, "ought:to": {"do": 1}, "to:do": {"more": 1, "it": 1, "a": 1}, "do:more": {"than": 1}, "more:than": {"just": 1}, "than:just": {"change": 1}, "just:change": {"our": 1}, "change:our": {"logo": 1}, "the:movement": {"to": 1}, "movement:to": {"rerestore": 1}, "to:rerestore": {"our": 1}, "rerestore:our": {"nation": 1}, "our:nation": {"is": 1}, "nation:is": {"honor": 1}, "is:honor": {"is": 1}, "honor:is": {"picking": 1}, "is:picking": {"up": 1}, "picking:up": {"steam": 1}, "you:reddit": {"thank": 1}, "reddit:thank": {"you": 1}, "off:the": {"beaten": 1, "boredom": 1}, "the:beaten": {"path": 1}, "beaten:path": {"smaller": 1}, "path:smaller": {"subreddits": 1}, "smaller:subreddits": {"worth": 1}, "subreddits:worth": {"a": 1}, "worth:a": {"visit": 1}, "cispa:and": {"cybersecurity": 1}, "and:cybersecurity": {"bills": 1}, "cybersecurity:bills": {"are": 1}, "bills:are": {"looming": 1}, "are:looming": {"we": 1}, "looming:we": {"are": 1}, "are:going": {"to": 1}, "going:to": {"need": 1, "be": 2}, "to:need": {"a": 1}, "need:a": {"montage": 1}, "decimating:our": {"ads": 1}, "our:ads": {"revenue": 1}, "fundraising:for": {"reddit": 1}, "potus:iama": {"stats": 1}, "in:helping": {"one": 1}, "helping:one": {"of": 1}, "one:of": {"our": 1}, "wbur:s": {"redditthemed": 1}, "s:redditthemed": {"podcast": 1}, "redditthemed:podcast": {"endless": 1}, "podcast:endless": {"thread": 1}, "endless:thread": {"debuts": 1}, "thread:debuts": {"its": 1}, "debuts:its": {"premiere": 1}, "its:premiere": {"episode": 1}, "rally:to": {"restore": 1}, "to:restore": {"your": 1}, "restore:your": {"rights": 1}, "your:rights": {"on": 1}, "rights:on": {"july": 1}, "day:one": {"week": 1}, "one:week": {"away": 1, "later": 1}, "the:gold": {"standard": 1}, "is:privacy": {"policy": 1}, "privacy:policy": {"has": 1}, "policy:has": {"been": 1}, "has:been": {"rewritten": 1, "the": 1}, "been:rewritten": {"from": 1}, "rewritten:from": {"the": 1}, "from:the": {"ground": 1}, "the:ground": {"up": 1}, "ground:up": {"come": 1}, "up:come": {"check": 1}, "come:check": {"it": 2}, "check:it": {"out": 2}, "university:of": {"reddit": 1}, "reddit:explore": {"any": 1}, "explore:any": {"subject": 1}, "any:subject": {"that": 1}, "subject:that": {"interests": 1}, "that:interests": {"you": 1}, "a:necessary": {"change": 1}, "necessary:change": {"in": 1}, "change:in": {"policy": 1}, "now:holds": {"a": 1}, "holds:a": {"guinness": 1}, "a:guinness": {"world": 1}, "world:s": {"record": 1}, "baby:it": {"is": 1}, "is:cold": {"outside": 1}, "cold:outside": {"subreddits": 1}, "outside:subreddits": {"to": 1}, "subreddits:to": {"get": 1}, "to:get": {"you": 2}, "get:you": {"through": 1, "started": 1}, "santas:in": {"countries": 2}, "in:countries": {"spread": 1, "are": 1, "be": 1}, "countries:spread": {"joy": 1}, "spread:joy": {"through": 1}, "joy:through": {"redditgifts": 1}, "reddit:acts": {"of": 1}, "acts:of": {"kindness": 1}, "of:kindness": {"reallife": 1}, "kindness:reallife": {"karma": 1}, "reallife:karma": {"part": 1, "an": 1}, "karma:part": {"now": 1}, "part:now": {"with": 1}, "now:with": {"more": 1}, "with:more": {"good": 1, "guinness": 1}, "gifts:summer": {"secret": 1}, "santa:back": {"participate": 1}, "back:participate": {"in": 1}, "is:that": {"lassie": 1, "arbitrary": 1, "time": 1}, "that:lassie": {"the": 1}, "lassie:the": {"old": 1}, "the:old": {"defaults": 1}, "old:defaults": {"fell": 1}, "defaults:fell": {"down": 1}, "fell:down": {"a": 1}, "down:a": {"well": 1, "border": 1}, "reddit:secret": {"santa": 2, "santas": 1}, "is:open": {"for": 2}, "open:for": {"signups": 2}, "for:signups": {"this": 1}, "signups:this": {"year": 1}, "year:with": {"more": 1}, "more:guinness": {"world": 1}, "snoo:wants": {"to": 1}, "wants:to": {"come": 1, "do": 1}, "to:come": {"home": 1}, "come:home": {"with": 1}, "home:with": {"you": 1}, "with:you": {"for": 1}, "you:for": {"the": 1}, "what:i": {"learned": 1}, "i:learned": {"from": 1}, "learned:from": {"chatting": 1}, "from:chatting": {"with": 1}, "chatting:with": {"strangers": 1}, "with:strangers": {"on": 1}, "strangers:on": {"the": 1}, "you:requested": {"him": 1}, "requested:him": {"and": 1}, "him:and": {"we": 1, "pet": 1, "squeeze": 1}, "and:we": {"got": 1}, "we:got": {"him": 1}, "got:him": {"ask": 1}, "him:ask": {"noam": 1}, "ask:noam": {"chomsky": 1}, "noam:chomsky": {"anything": 1, "answers": 1}, "chomsky:anything": {"reddit": 1}, "anything:reddit": {"video": 3}, "reddit:video": {"interview": 3}, "top:posts": {"of": 2}, "posts:of": {"the": 1, "stats": 1}, "of:the": {"year": 2, "most": 1, "servers": 1, "real": 1, "life": 1, "last": 1, "best": 2, "combined": 1, "word": 1, "tapes": 1, "finalists": 1, "hive": 1, "shirts": 1}, "the:year": {"and": 1, "ends": 1}, "year:and": {"the": 1}, "internet:bus": {"tour": 1}, "bus:tour": {"a": 1}, "tour:a": {"campaign": 1}, "a:campaign": {"to": 1}, "campaign:to": {"promote": 1}, "to:promote": {"the": 1}, "promote:the": {"open": 1}, "the:open": {"internet": 1, "source": 1}, "how:to": {"use": 1, "tell": 1}, "to:use": {"reddittv": 1}, "use:reddittv": {"and": 1}, "reddittv:and": {"a": 1}, "and:a": {"sampling": 1, "fun": 1, "few": 1, "personal": 1}, "a:sampling": {"of": 1}, "sampling:of": {"the": 1}, "the:most": {"popular": 1, "reddit": 1}, "most:popular": {"videos": 1}, "popular:videos": {"and": 1}, "videos:and": {"channels": 1, "being": 1}, "and:channels": {"to": 1}, "channels:to": {"get": 1}, "reflections:on": {"the": 1}, "the:recent": {"boston": 1}, "recent:boston": {"crisis": 1}, "the:annual": {"global": 3}, "annual:global": {"reddit": 5}, "is:saturday": {"june": 1}, "redditors:all": {"around": 1}, "all:around": {"the": 1}, "world:make": {"the": 1}, "make:the": {"world": 1}, "world:spin": {"right": 1}, "spin:right": {"round": 1}, "right:round": {"right": 1}, "round:right": {"round": 1}, "cheaters:never": {"win": 1}, "is:official": {"statement": 1}, "official:statement": {"on": 1}, "statement:on": {"prop": 1}, "on:prop": {"ads": 1}, "now:sharing": {"absurdity": 1}, "sharing:absurdity": {"the": 1}, "absurdity:the": {"nsa": 1}, "the:nsa": {"gift": 1}, "nsa:gift": {"exchange": 1}, "us:before": {"it": 1}, "before:it": {"s": 1}, "it:s": {"too": 1, "time": 1}, "s:too": {"late": 1}, "late:play": {"games": 1}, "games:and": {"heal": 2, "help": 1}, "and:heal": {"kids": 2}, "heal:kids": {"with": 1, "extra": 1}, "kids:with": {"extra": 1}, "with:extra": {"life": 1}, "of:stats": {"and": 1}, "stats:and": {"snoo": 1}, "and:snoo": {"year": 1}, "snoo:year": {"is": 1}, "new:default": {"subreddits": 1}, "default:subreddits": {"omgomgomg": 1}, "karma:an": {"update": 1}, "on:some": {"altruistic": 1}, "some:altruistic": {"stories": 1}, "it:we": {"set": 1}, "we:set": {"another": 1}, "set:another": {"guinness": 1}, "another:guinness": {"world": 1}, "and:like": {"that": 1}, "like:that": {"poof": 1}, "that:poof": {"he": 1}, "poof:he": {"is": 1}, "he:is": {"gone": 1}, "headdit:a": {"revolutionary": 1}, "a:revolutionary": {"new": 1}, "revolutionary:new": {"way": 1}, "new:way": {"to": 1}, "to:browse": {"reddit": 1}, "is:creative": {"communities": 1}, "creative:communities": {"with": 1}, "communities:with": {"added": 1}, "with:added": {"statue": 1}, "added:statue": {"selfies": 1}, "top:amas": {"on": 1}, "amas:on": {"riama": 1}, "reddit:it": {"is": 2}, "for:us": {"to": 1}, "us:to": {"move": 1, "play": 1}, "to:move": {"on": 1}, "move:on": {"to": 1}, "on:to": {"bigger": 1}, "to:bigger": {"better": 1}, "bigger:better": {"things": 1}, "teachers:with": {"classroom": 1}, "with:classroom": {"supplies": 1}, "classroom:supplies": {"in": 1}, "supplies:in": {"our": 1}, "in:our": {"annual": 2}, "tradition:break": {"a": 1}, "record:reddit": {"secret": 1}, "reddit:companion": {"for": 1}, "companion:for": {"chrome": 1}, "the:watching": {"of": 1}, "watching:of": {"videos": 1}, "of:videos": {"and": 1}, "and:being": {"a": 1}, "being:a": {"default": 1}, "a:default": {"subreddit": 1}, "reddit:billions": {"served": 1}, "january:state": {"of": 1}, "state:of": {"the": 1, "footballsoccer": 1}, "renew:your": {"resolutions": 1}, "you:decide": {"reddit": 1}, "decide:reddit": {"is": 1}, "is:best": {"of": 4}, "new:reddit": {"ceo": 1}, "reddit:ceo": {"reporting": 1}, "ceo:reporting": {"for": 1}, "reporting:for": {"duty": 1}, "here:again": {"sign": 1}, "again:sign": {"up": 1}, "sign:up": {"for": 3}, "up:for": {"the": 1, "secret": 1, "a": 1}, "the:summer": {"secret": 1}, "lucas:inspires": {"reddit": 1}, "now:is": {"the": 1}, "the:time": {"to": 1}, "to:invest": {"in": 1}, "invest:in": {"gold": 1}, "over:reddit": {"secret": 1}, "secret:santas": {"in": 1}, "countries:are": {"sending": 1}, "are:sending": {"gifts": 1}, "sending:gifts": {"to": 1}, "gifts:to": {"spread": 1, "each": 1}, "to:spread": {"happiness": 1}, "spread:happiness": {"and": 1}, "happiness:and": {"set": 1}, "and:set": {"a": 2}, "set:a": {"world": 1, "new": 1}, "a:group": {"of": 1}, "group:of": {"redditors": 1}, "of:redditors": {"is": 1}, "redditors:is": {"taking": 1}, "is:taking": {"a": 1}, "taking:a": {"stand": 1}, "a:stand": {"against": 1}, "stand:against": {"backscatter": 1}, "against:backscatter": {"xrays": 1}, "backscatter:xrays": {"and": 1}, "xrays:and": {"tsa": 1}, "and:tsa": {"patdowns": 1}, "coming:join": {"us": 1}, "us:november": {"and": 1}, "november:and": {"help": 1}, "and:help": {"raise": 1, "sick": 1, "restore": 1}, "help:raise": {"money": 1}, "into:the": {"lions": 1, "exhilaration": 1}, "the:lions": {"den": 1}, "continue:to": {"be": 1}, "to:be": {"astounded": 1, "june": 1, "at": 1}, "be:astounded": {"plus": 1}, "astounded:plus": {"some": 1}, "plus:some": {"answers": 1, "stats": 1}, "some:answers": {"to": 1}, "answers:to": {"common": 1}, "to:common": {"questions": 1}, "announcing:redditor": {"artists": 1}, "redditor:artists": {"supporting": 1}, "artists:supporting": {"charity": 2}, "supporting:charity": {"first": 1, "tim": 1}, "charity:first": {"up": 1}, "first:up": {"shirts": 1}, "up:shirts": {"by": 1}, "shirts:by": {"shittywatercolour": 1}, "by:shittywatercolour": {"and": 1}, "shittywatercolour:and": {"youngluck": 1}, "and:youngluck": {"supporting": 1}, "youngluck:supporting": {"watsi": 1}, "take:me": {"out": 1}, "me:out": {"to": 1}, "out:to": {"the": 1}, "the:insert": {"sport": 1}, "insert:sport": {"here": 1}, "sport:here": {"game": 1}, "coming:up": {"soon": 1}, "up:soon": {"on": 1}, "soon:on": {"saturday": 1}, "on:saturday": {"june": 2}, "find:a": {"meetup": 1}, "a:meetup": {"here": 1}, "reddit:dedicated": {"day": 1}, "dedicated:day": {"of": 1}, "day:of": {"service": 1, "the": 1, "games": 1}, "of:service": {"rddos": 1}, "service:rddos": {"this": 1}, "rddos:this": {"saturday": 1}, "for:secret": {"santa": 1}, "santa:now": {"help": 1}, "now:help": {"break": 1}, "break:the": {"guinness": 1}, "the:guinness": {"world": 1}, "a:typical": {"meeting": 1}, "typical:meeting": {"of": 1}, "meeting:of": {"the": 1}, "the:real": {"reddit": 1}, "real:reddit": {"admins": 1}, "billion:and": {"beyond": 1}, "the:next": {"generation": 1}, "next:generation": {"of": 1}, "generation:of": {"reddit": 1}, "promote:your": {"crowdfunded": 1}, "your:crowdfunded": {"project": 1}, "crowdfunded:project": {"on": 1}, "project:on": {"reddit": 1}, "on:reddit": {"for": 1, "told": 1, "sorry": 1}, "this:april": {"fool": 1}, "april:fool": {"is": 1}, "fool:is": {"day": 1}, "is:day": {"give": 1}, "day:give": {"the": 1}, "give:the": {"gift": 1}, "the:gift": {"of": 1}, "gift:of": {"reddit": 1}, "nerd:talk": {"the": 1}, "talk:the": {"tale": 1}, "the:tale": {"of": 1}, "tale:of": {"the": 1}, "the:life": {"of": 1, "at": 1}, "life:of": {"a": 1}, "of:a": {"link": 1}, "a:link": {"on": 1}, "link:on": {"reddit": 1}, "reddit:told": {"in": 1}, "told:in": {"graph": 1}, "in:graph": {"porn": 1}, "to:play": {"games": 2}, "kids:extra": {"life": 1}, "which:cities": {"countries": 1}, "cities:countries": {"have": 1}, "have:the": {"most": 1}, "most:reddit": {"addicts": 1}, "this:nov": {"reddit": 1}, "nov:reddit": {"is": 1}, "is:livestream": {"brings": 1, "black": 1}, "livestream:brings": {"the": 1}, "brings:the": {"black": 1}, "the:black": {"friday": 1}, "black:friday": {"chaos": 1, "show": 1}, "friday:chaos": {"to": 1}, "chaos:to": {"you": 1}, "just:clearing": {"up": 1}, "clearing:up": {"a": 1}, "up:a": {"few": 1}, "a:few": {"misconceptions": 1, "more": 1, "of": 1, "live": 1}, "all:good": {"things": 1}, "have:rewritten": {"our": 1}, "rewritten:our": {"user": 1}, "our:user": {"agreement": 1}, "user:agreement": {"come": 1}, "agreement:come": {"check": 1}, "it:out": {"we": 1}, "out:we": {"want": 1}, "ready:to": {"participate": 1}, "to:participate": {"in": 1}, "in:the": {"universe": 1, "world": 3, "life": 1, "final": 1, "sidebar": 1, "armed": 1}, "the:universe": {"is": 1}, "universe:is": {"largest": 1}, "is:largest": {"secret": 1}, "santa:program": {"secret": 1}, "program:secret": {"santa": 1}, "santa:sign": {"ups": 1}, "sign:ups": {"start": 1}, "ups:start": {"today": 1}, "a:special": {"guest": 1, "redditgifts": 1}, "special:guest": {"post": 1}, "guest:post": {"on": 1}, "post:on": {"misguided": 1}, "on:misguided": {"vigilantism": 1}, "quick:update": {"about": 1}, "update:about": {"ads": 1}, "about:ads": {"on": 1}, "ads:on": {"reddit": 1}, "re:back": {"for": 1}, "back:for": {"more": 1}, "for:more": {"extra": 1}, "more:extra": {"life": 1}, "life:come": {"join": 1}, "come:join": {"us": 1}, "holidays:you": {"filthy": 1, "glorious": 1}, "you:filthy": {"animals": 1}, "santa:was": {"fun": 1}, "was:fun": {"now": 1}, "fun:now": {"it": 1}, "now:it": {"s": 1}, "s:time": {"to": 1}, "do:it": {"again": 1}, "again:with": {"arbitrary": 1}, "with:arbitrary": {"day": 1}, "annual:world": {"backup": 2}, "world:backup": {"day": 3}, "backup:day": {"what": 1, "is": 1, "reddit": 1}, "day:what": {"is": 1}, "is:in": {"reddit": 1}, "in:reddit": {"is": 3}, "is:backup": {"this": 1}, "backup:this": {"week": 1}, "this:week": {"in": 1}, "week:in": {"addition": 1}, "in:addition": {"to": 1}, "addition:to": {"invocations": 1}, "to:invocations": {"of": 1}, "invocations:of": {"amurica": 1}, "new:fundraising": {"options": 1}, "fundraising:options": {"designed": 1}, "options:designed": {"just": 1}, "designed:just": {"for": 1}, "just:for": {"redditors": 1, "shirts": 1}, "and:now": {"for": 1}, "now:for": {"a": 1}, "for:a": {"word": 1, "special": 1}, "a:word": {"from": 1}, "word:from": {"our": 1}, "from:our": {"sponsor": 1}, "our:sponsor": {"because": 1}, "sponsor:because": {"for": 1}, "because:for": {"once": 1}, "for:once": {"we": 1}, "once:we": {"have": 1}, "have:one": {"asking": 1}, "one:asking": {"to": 1}, "asking:to": {"hear": 1}, "to:hear": {"your": 1}, "hear:your": {"feedback": 1}, "of:fundraising": {"and": 1}, "fundraising:and": {"altruism": 1}, "and:altruism": {"on": 1}, "altruism:on": {"reddit": 1}, "down:for": {"the": 1, "of": 1, "minutes": 1, "quick": 1}, "the:count": {"a": 1}, "count:a": {"look": 1}, "a:look": {"inside": 1}, "look:inside": {"the": 1}, "inside:the": {"odd": 1}, "the:odd": {"world": 1}, "odd:world": {"of": 1}, "world:of": {"rlivecounting": 1}, "day:v": {"some": 1, "is": 1}, "v:some": {"stats": 1}, "some:stats": {"on": 1, "about": 1}, "stats:on": {"top": 1}, "on:top": {"cities": 1}, "six:new": {"redditgifts": 1, "exchanges": 1}, "new:redditgifts": {"exchanges": 1}, "redditgifts:exchanges": {"to": 1}, "exchanges:to": {"start": 1}, "to:start": {"off": 1}, "start:off": {"books": 1}, "off:books": {"snacks": 1}, "books:snacks": {"coffee": 1}, "snacks:coffee": {"tea": 1}, "coffee:tea": {"pokemon": 1}, "tea:pokemon": {"socks": 1}, "pokemon:socks": {"hats": 1}, "socks:hats": {"scarves": 1}, "make:someone": {"happy": 1}, "someone:happy": {"and": 1}, "happy:and": {"set": 1}, "new:guinness": {"world": 1}, "record:in": {"our": 1}, "holiday:greeting": {"card": 2}, "greeting:card": {"exchange": 2}, "day:signups": {"are": 2}, "new:create": {"and": 1}, "create:and": {"share": 1}, "and:share": {"your": 1}, "share:your": {"own": 1}, "own:collections": {"of": 1}, "collections:of": {"subreddits": 1}, "of:subreddits": {"using": 1}, "subreddits:using": {"multireddits": 1}, "announcing:season": {"of": 1}, "season:of": {"reddit": 1}, "s:internship": {"program": 1}, "help:sick": {"kids": 1}, "why:do": {"experts": 1}, "do:experts": {"misunderestimate": 1}, "experts:misunderestimate": {"the": 1}, "misunderestimate:the": {"size": 1}, "the:size": {"of": 2}, "size:of": {"reddit": 1, "its": 1}, "redditcom:interviews": {"christopher": 1}, "interviews:christopher": {"hitchens": 1}, "the:tshirt": {"exchange": 1}, "tshirt:exchange": {"also": 1}, "exchange:also": {"fantasy": 1}, "also:fantasy": {"horror": 1}, "fantasy:horror": {"manga": 1}, "horror:manga": {"adventure": 1}, "manga:adventure": {"time": 1}, "adventure:time": {"and": 1}, "time:and": {"yarn": 1}, "be:a": {"frontend": 1}, "a:frontend": {"engineer": 1}, "frontend:engineer": {"at": 1}, "engineer:at": {"reddit": 1}, "who:in": {"the": 2}, "world:is": {"reddit": 2}, "why:reddit": {"was": 1}, "reddit:was": {"down": 1}, "was:down": {"for": 1}, "for:of": {"the": 1}, "the:last": {"hours": 1}, "reddit:buys": {"team": 1}, "buys:team": {"fortress": 1}, "a:day": {"in": 1, "for": 1}, "day:in": {"the": 1}, "life:at": {"reddit": 1}, "at:reddit": {"hq": 1}, "a:server": {"by": 1}, "server:by": {"any": 1}, "by:any": {"other": 1}, "any:other": {"name": 1}, "blogreddit:and": {"a": 1}, "a:fun": {"weekend": 1}, "fun:weekend": {"was": 1}, "weekend:was": {"had": 1}, "was:had": {"by": 1}, "had:by": {"all": 1}, "what:was": {"that": 1}, "was:that": {"peers": 1}, "that:peers": {"down": 1}, "peers:down": {"the": 1}, "down:the": {"basement": 1}, "the:basement": {"stairs": 1}, "good:news": {"everyone": 1}, "reddit:helps": {"with": 1}, "helps:with": {"your": 1}, "with:your": {"new": 1}, "your:new": {"year": 1}, "new:year": {"is": 1}, "s:communities": {"in": 1}, "reddit:joins": {"the": 1}, "joins:the": {"free": 1}, "free:software": {"foundation": 1}, "software:foundation": {"help": 1}, "foundation:help": {"us": 1}, "us:design": {"an": 1}, "design:an": {"ad": 1}, "an:ad": {"for": 1, "on": 1}, "ad:for": {"fsf": 1}, "new:holiday": {"tradition": 1}, "holiday:tradition": {"reddit": 1}, "tradition:reddit": {"holiday": 1}, "reddit:holiday": {"greeting": 1}, "card:exchange": {"is": 1}, "exchange:is": {"open": 1}, "get:ready": {"global": 1, "for": 1}, "ready:global": {"reddit": 1}, "v:is": {"going": 1}, "is:going": {"to": 1}, "i:am": {"putting": 1}, "am:putting": {"the": 1}, "putting:the": {"reddit": 1}, "alien:on": {"a": 1}, "on:a": {"bus": 1, "podcast": 1, "debate": 1}, "a:bus": {"and": 1}, "bus:and": {"doing": 1}, "and:doing": {"a": 1}, "doing:a": {"stop": 1, "video": 1}, "a:stop": {"college": 1}, "stop:college": {"month": 1}, "college:month": {"long": 1}, "month:long": {"tour": 1}, "long:tour": {"for": 1}, "tour:for": {"internet": 1}, "for:internet": {"entrepreneurship": 1}, "internet:entrepreneurship": {"let": 1}, "entrepreneurship:let": {"is": 1}, "let:is": {"hang": 1, "play": 1, "recognize": 1}, "is:hang": {"out": 1}, "day:iii": {"this": 1}, "iii:this": {"saturday": 1}, "that:arbitrary": {"time": 1}, "arbitrary:time": {"of": 1}, "time:of": {"year": 1}, "of:year": {"when": 1}, "year:when": {"redditors": 1}, "when:redditors": {"send": 1}, "redditors:send": {"arbitrary": 1}, "send:arbitrary": {"gifts": 1}, "arbitrary:gifts": {"to": 1}, "to:each": {"other": 1}, "each:other": {"arbitrary": 1, "for": 1}, "other:arbitrary": {"day": 1}, "gold:payment": {"options": 1}, "payment:options": {"bitcoin": 1}, "options:bitcoin": {"and": 1}, "bitcoin:and": {"credit": 1}, "and:credit": {"card": 1}, "redditcon:if": {"we": 1}, "if:we": {"build": 1}, "we:build": {"it": 1}, "build:it": {"will": 1}, "it:will": {"you": 1}, "that:time": {"again": 1}, "time:again": {"extra": 1}, "again:extra": {"life": 1}, "some:curated": {"content": 1}, "curated:content": {"to": 1}, "content:to": {"stave": 1}, "to:stave": {"off": 1}, "stave:off": {"the": 1}, "is:play": {"some": 1}, "play:some": {"games": 1}, "some:games": {"reddit": 1}, "games:reddit": {"it": 1}, "few:more": {"gold": 1}, "more:gold": {"benefits": 1}, "list:plus": {"posters": 1}, "plus:posters": {"and": 1}, "posters:and": {"name": 1}, "and:name": {"tags": 1}, "name:tags": {"inside": 1}, "day:will": {"be": 1}, "be:this": {"weekend": 1}, "this:weekend": {"in": 1}, "weekend:in": {"over": 1}, "in:over": {"cities": 2, "countries": 1}, "over:cities": {"in": 1, "for": 1}, "cities:in": {"countries": 1}, "countries:be": {"there": 1}, "the:stephen": {"colbert": 1}, "colbert:interview": {"is": 1}, "interview:is": {"now": 1}, "to:choose": {"the": 2}, "choose:the": {"winners": 2}, "winners:in": {"reddit": 2}, "another:update": {"on": 1}, "welcome:andy": {"ashley": 1}, "andy:ashley": {"cameron": 1}, "ashley:cameron": {"jordan": 1}, "cameron:jordan": {"michael": 1}, "jordan:michael": {"greg": 1}, "michael:greg": {"rachael": 1}, "greg:rachael": {"and": 1}, "rachael:and": {"zubair": 1}, "helping:the": {"economy": 1}, "the:economy": {"one": 1}, "economy:one": {"hiring": 1}, "one:hiring": {"campaign": 1}, "hiring:campaign": {"at": 1}, "campaign:at": {"a": 1}, "at:a": {"time": 1}, "introducing:three": {"new": 1}, "three:new": {"hires": 1, "programmers": 1}, "millions:ask": {"anything": 1}, "important:reddit": {"announcement": 1}, "reddit:service": {"day": 3}, "service:day": {"global": 1, "on": 1, "october": 1}, "day:global": {"cardboard": 1, "reddit": 1}, "global:cardboard": {"challenge": 1}, "cardboard:challenge": {"are": 1}, "challenge:are": {"coming": 1}, "are:coming": {"october": 1}, "reddit:resources": {"and": 1}, "resources:and": {"subreddit": 1}, "and:subreddit": {"ads": 1}, "us:each": {"other": 1}, "other:for": {"the": 1}, "day:on": {"october": 1, "june": 1}, "is:on": {"june": 1}, "on:june": {"start": 1, "plus": 1}, "june:start": {"organizing": 1}, "let:the": {"games": 1}, "the:games": {"begin": 1}, "games:begin": {"a": 1}, "begin:a": {"chooseyourownblog": 1}, "a:chooseyourownblog": {"adventure": 1}, "the:colbertstewart": {"march": 1}, "colbertstewart:march": {"rally": 1}, "reddit:levels": {"up": 1}, "levels:up": {"with": 1}, "up:with": {"three": 1}, "with:three": {"new": 1}, "over:teachers": {"need": 1}, "teachers:need": {"your": 1}, "a:cause": {"worthy": 1}, "cause:worthy": {"of": 1}, "worthy:of": {"rallying": 1}, "of:rallying": {"let": 1}, "rallying:let": {"s": 1}, "s:get": {"reading": 1, "kids": 1}, "get:reading": {"let": 1}, "reading:let": {"s": 1}, "get:kids": {"reading": 1}, "cyber:monday": {"happening": 1}, "monday:happening": {"now": 1}, "happening:now": {"four": 1}, "now:four": {"flash": 1}, "four:flash": {"sales": 1}, "flash:sales": {"in": 1}, "sales:in": {"hours": 1}, "in:hours": {"with": 1}, "hours:with": {"the": 1}, "with:the": {"best": 1, "world": 1}, "best:discounts": {"of": 1}, "discounts:of": {"the": 1}, "year:ends": {"est": 1}, "you:glorious": {"bastards": 1}, "time:is": {"running": 2}, "is:running": {"out": 2}, "running:out": {"extra": 1, "help": 1}, "out:extra": {"life": 1}, "ready:for": {"global": 1}, "for:global": {"reddit": 1}, "june:plus": {"some": 1}, "stats:about": {"top": 1}, "about:top": {"reddit": 1}, "top:reddit": {"cities": 1}, "reddit:cities": {"and": 1}, "cities:and": {"languages": 1}, "vote:now": {"in": 1}, "now:in": {"the": 1}, "the:final": {"round": 1, "day": 1, "ballots": 1}, "final:round": {"of": 1}, "round:of": {"the": 1}, "today:is": {"the": 1}, "final:day": {"of": 1}, "the:combined": {"community": 1}, "combined:community": {"charity": 1}, "community:charity": {"challenge": 1}, "charity:challenge": {"which": 1}, "challenge:which": {"team": 1}, "which:team": {"are": 1}, "team:are": {"you": 1}, "are:you": {"on": 1, "going": 1}, "congratulations:to": {"reddit": 1}, "one:hundred": {"gift": 1}, "hundred:gift": {"exchanges": 1}, "gift:exchanges": {"a": 1, "meet": 1}, "exchanges:a": {"celebration": 1}, "a:celebration": {"extravaganzapalooza": 1}, "out:help": {"us": 1}, "us:support": {"extra": 1}, "support:extra": {"life": 1}, "every:man": {"is": 1}, "man:is": {"responsible": 1}, "is:responsible": {"for": 1}, "responsible:for": {"his": 1}, "for:his": {"own": 1}, "his:own": {"soul": 1}, "reddit:mailbag": {"tldr": 1}, "mailbag:tldr": {"just": 1}, "tldr:just": {"look": 1}, "just:look": {"at": 1}, "look:at": {"the": 1}, "the:pretty": {"pictures": 1}, "reddit:acquires": {"redditgiftscom": 1}, "acquires:redditgiftscom": {"to": 1}, "redditgiftscom:to": {"support": 1}, "support:secret": {"santa": 1}, "santa:more": {"gift": 1}, "more:gift": {"exchanges": 1}, "exchanges:meet": {"ups": 1}, "meet:ups": {"and": 1}, "ups:and": {"beyond": 1}, "new:reddits": {"are": 1}, "reddits:are": {"getting": 1}, "are:getting": {"some": 1}, "getting:some": {"pimp": 1}, "some:pimp": {"love": 1}, "votes:later": {"and": 1}, "later:and": {"voting": 1}, "and:voting": {"was": 1}, "voting:was": {"a": 1}, "was:a": {"sockcess": 1}, "congressman:dennis": {"kucinich": 1}, "dennis:kucinich": {"answers": 1}, "kucinich:answers": {"your": 1}, "answers:your": {"questions": 7, "top": 4}, "if:you": {"are": 1}, "are:a": {"nonprofit": 1, "few": 1}, "a:nonprofit": {"organization": 1}, "nonprofit:organization": {"we": 1}, "organization:we": {"have": 1}, "have:some": {"free": 1}, "some:free": {"ad": 1}, "free:ad": {"space": 1, "campaigns": 1}, "ad:space": {"for": 1}, "space:for": {"you": 1}, "reddit:needs": {"a": 1}, "needs:a": {"new": 1}, "new:motto": {"or": 1}, "motto:or": {"maybe": 1}, "or:maybe": {"it": 1}, "maybe:it": {"does": 1}, "it:does": {"not": 1}, "welcome:lilly": {"nicole": 1}, "lilly:nicole": {"chris": 1}, "nicole:chris": {"ismail": 1}, "chris:ismail": {"erica": 1}, "ismail:erica": {"cynthia": 1}, "erica:cynthia": {"max": 1}, "cynthia:max": {"and": 1}, "max:and": {"chris": 1}, "test:socks": {"please": 1}, "socks:please": {"ignore": 1}, "socialite:for": {"firefox": 1}, "bringing:more": {"benefits": 1}, "more:benefits": {"to": 1}, "benefits:to": {"reddit": 1}, "reddit:gold": {"members": 1, "now": 1}, "upgrading:our": {"selfserve": 1}, "our:selfserve": {"system": 1, "advertising": 1}, "remaking:our": {"selfserve": 1}, "selfserve:advertising": {"system": 1}, "everyone:on": {"team": 1}, "on:team": {"reddit": 1}, "reddit:would": {"like": 1}, "would:like": {"to": 1}, "like:to": {"raise": 1}, "raise:a": {"toast": 1}, "a:toast": {"to": 1}, "toast:to": {"jedberg": 1}, "to:jedberg": {"and": 1}, "jedberg:and": {"the": 1}, "the:missus": {"in": 1}, "missus:in": {"celebration": 1}, "in:celebration": {"of": 1}, "celebration:of": {"their": 1}, "of:their": {"embarkation": 1}, "their:embarkation": {"into": 1}, "embarkation:into": {"the": 1}, "the:exhilaration": {"that": 1}, "exhilaration:that": {"is": 1}, "that:is": {"married": 1}, "is:married": {"life": 1}, "is:help": {"the": 1}, "help:the": {"internet": 1}, "internet:just": {"broke": 1}, "just:broke": {"down": 1}, "broke:down": {"a": 1}, "a:border": {"on": 1}, "border:on": {"an": 1}, "an:unrelated": {"note": 1}, "unrelated:note": {"two": 1}, "note:two": {"reddit": 1}, "two:reddit": {"guys": 1}, "reddit:guys": {"were": 1}, "guys:were": {"guests": 1}, "were:guests": {"on": 1}, "guests:on": {"a": 1}, "a:podcast": {"last": 1}, "podcast:last": {"night": 1}, "we:hardly": {"knew": 1}, "hardly:knew": {"ye": 1}, "halloween:is": {"near": 1}, "is:near": {"new": 1}, "near:new": {"exchanges": 1}, "new:exchanges": {"halloween": 1, "on": 1}, "exchanges:halloween": {"dr": 1}, "halloween:dr": {"who": 1}, "dr:who": {"decorate": 1}, "who:decorate": {"my": 1}, "decorate:my": {"cube": 1}, "my:cube": {"postcards": 1}, "cube:postcards": {"and": 1}, "postcards:and": {"more": 1}, "is:upon": {"us": 1}, "the:day": {"of": 1}, "of:games": {"is": 1}, "games:is": {"nigh": 1}, "is:nigh": {"extralife": 1}, "nigh:extralife": {"marathon": 1}, "are:crossing": {"the": 1}, "crossing:the": {"streams": 1}, "the:streams": {"june": 1}, "streams:june": {"is": 1}, "june:is": {"arbitrary": 1}, "is:arbitrary": {"day": 1}, "welcome:tiffany": {"dane": 1}, "tiffany:dane": {"michele": 1}, "dane:michele": {"george": 1}, "michele:george": {"donall": 1}, "george:donall": {"heath": 1}, "donall:heath": {"andrew": 1}, "heath:andrew": {"alexandr": 1}, "looking:for": {"smart": 1}, "for:smart": {"talented": 1}, "smart:talented": {"and": 1}, "talented:and": {"well": 1}, "and:well": {"informed": 1}, "well:informed": {"candidates": 1}, "informed:candidates": {"run": 1}, "candidates:run": {"a": 1}, "run:a": {"free": 1}, "a:free": {"for": 1}, "free:for": {"hire": 1}, "for:hire": {"ad": 1}, "hire:ad": {"on": 1}, "ad:on": {"reddit": 2}, "welcome:drew": {"ryan": 1}, "drew:ryan": {"mike": 1}, "ryan:mike": {"daniel": 1}, "mike:daniel": {"joe": 1}, "daniel:joe": {"dave": 1}, "joe:dave": {"david": 1}, "saying:goodbye": {"to": 1}, "goodbye:to": {"an": 1}, "to:an": {"old": 1, "ipod": 1}, "an:old": {"friend": 1}, "old:friend": {"and": 1}, "friend:and": {"revising": 1}, "and:revising": {"the": 1}, "revising:the": {"default": 1}, "the:default": {"subreddits": 1}, "ad:campaigns": {"for": 1}, "campaigns:for": {"international": 1}, "for:international": {"advertisers": 1}, "what:a": {"day": 1}, "day:for": {"reddit": 1}, "for:reddit": {"engineering": 1}, "new:shirts": {"from": 1}, "shirts:from": {"reddit": 1}, "from:reddit": {"artists": 1}, "reddit:artists": {"supporting": 1}, "charity:tim": {"doyle": 1}, "tim:doyle": {"and": 1}, "doyle:and": {"ujuliankelly": 1}, "and:ujuliankelly": {"supporting": 1}, "ujuliankelly:supporting": {"cpi": 1}, "thanks:hackers": {"in": 1}, "hackers:in": {"both": 1}, "in:both": {"senses": 1}, "both:senses": {"of": 1}, "senses:of": {"the": 1}, "your:gold": {"dollars": 1}, "gold:dollars": {"at": 1}, "dollars:at": {"work": 1}, "everything:you": {"need": 1}, "you:need": {"to": 1}, "to:know": {"about": 1}, "know:about": {"saturday": 1, "the": 1}, "about:saturday": {"is": 1}, "saturday:is": {"rallies": 1}, "welcome:new": {"recruit": 1, "admin": 1}, "new:recruit": {"victoria": 1}, "recruit:victoria": {"keeper": 1}, "victoria:keeper": {"of": 1}, "keeper:of": {"the": 1}, "chomsky:answers": {"your": 1}, "your:questions": {"ask": 3, "video": 1, "and": 1}, "questions:ask": {"me": 3}, "ask:me": {"anything": 5}, "me:anything": {"video": 4, "volume": 1}, "anything:video": {"interview": 7}, "is:hiring": {"positions": 1, "again": 1}, "hiring:positions": {"redditgifts": 1}, "positions:redditgifts": {"programmer": 1}, "redditgifts:programmer": {"and": 1}, "programmer:and": {"controller": 1}, "and:controller": {"finance": 1}, "upcoming:meetup": {"global": 1}, "meetup:global": {"reddit": 1}, "all:local": {"businesses": 1}, "anything:volume": {"one": 1}, "welcome:johnwilliam": {"chris": 1}, "johnwilliam:chris": {"adam": 1}, "chris:adam": {"ryan": 1}, "adam:ryan": {"jennifer": 1}, "ryan:jennifer": {"nina": 1}, "jennifer:nina": {"melissa": 1}, "nina:melissa": {"justin": 1}, "melissa:justin": {"james": 1}, "redditors:assemble": {"in": 1}, "assemble:in": {"over": 1}, "cities:for": {"grmd": 1}, "for:grmd": {"iii": 1}, "grmd:iii": {"announcing": 1}, "iii:announcing": {"a": 1}, "announcing:a": {"new": 1}, "new:global": {"meetup": 1}, "global:meetup": {"rddos": 1}, "introducing:manualreddit": {"upvote": 1}, "manualreddit:upvote": {"your": 1}, "upvote:your": {"world": 1}, "your:world": {"with": 1}, "world:with": {"magnets": 1}, "welcome:to": {"jack": 1}, "to:jack": {"scott": 1}, "jack:scott": {"jaleh": 1}, "scott:jaleh": {"sean": 1}, "jaleh:sean": {"rich": 1}, "sean:rich": {"zean": 1}, "rich:zean": {"matt": 1}, "zean:matt": {"will": 1}, "matt:will": {"lisa": 1}, "will:name": {"him": 1}, "name:him": {"snoo": 1}, "him:snoo": {"and": 1}, "snoo:and": {"i": 1}, "and:i": {"will": 1}, "will:hug": {"him": 1}, "hug:him": {"and": 1}, "and:pet": {"him": 1}, "pet:him": {"and": 1}, "and:squeeze": {"him": 1}, "interrobang:your": {"wall": 1}, "your:wall": {"with": 1}, "wall:with": {"this": 1}, "with:this": {"new": 1}, "this:new": {"cuil": 1}, "new:cuil": {"theory": 1}, "cuil:theory": {"poster": 1}, "welcome:tavish": {"lindsey": 1}, "tavish:lindsey": {"and": 1}, "lindsey:and": {"nina": 1}, "day:reddit": {"backup": 1}, "reddit:backup": {"stats": 1}, "merry:christmas": {"or": 1}, "christmas:or": {"whathaveyou": 1}, "or:whathaveyou": {"from": 1}, "whathaveyou:from": {"all": 1}, "reddit:shirts": {"are": 1}, "shirts:are": {"back": 1}, "rirene:putting": {"reddit": 1}, "putting:reddit": {"to": 1}, "reddit:to": {"good": 1}, "to:good": {"use": 1}, "good:use": {"during": 1}, "use:during": {"a": 1}, "during:a": {"natural": 1}, "a:natural": {"disaster": 1}, "reddit:gets": {"a": 1}, "gets:a": {"big": 1}, "a:big": {"investment": 1}, "big:investment": {"in": 1}, "investment:in": {"headcount": 1}, "charting:the": {"super": 1}, "the:super": {"bowl": 1}, "super:bowl": {"through": 1}, "bowl:through": {"our": 1}, "through:our": {"traffic": 1}, "our:traffic": {"graph": 1}, "re:fighting": {"for": 1}, "fighting:for": {"marriage": 1}, "for:marriage": {"equality": 1}, "marriage:equality": {"in": 1}, "equality:in": {"utah": 1}, "in:utah": {"and": 1}, "utah:and": {"around": 1}, "and:around": {"the": 1}, "world:will": {"you": 1}, "why:did": {"we": 1}, "did:we": {"take": 1}, "we:take": {"reddit": 1}, "take:reddit": {"down": 1}, "reddit:down": {"for": 1}, "new:admin": {"deimorz": 1}, "who:would": {"you": 2}, "would:you": {"nominate": 2}, "you:nominate": {"for": 3}, "nominate:for": {"the": 3}, "announcing:new": {"additions": 1}, "new:additions": {"to": 1}, "additions:to": {"team": 1}, "to:team": {"reddit": 1}, "over:countries": {"went": 1}, "countries:went": {"afk": 1}, "went:afk": {"for": 1}, "afk:for": {"grmd": 1}, "introducing:the": {"reddit": 1, "open": 1}, "reddit:snoo": {"chullo": 1}, "snoo:chullo": {"hat": 1}, "new:employees": {"appear": 1}, "employees:appear": {"welcome": 1}, "appear:welcome": {"mike": 1}, "welcome:mike": {"dylan": 1}, "the:servers": {"rejoiced": 1}, "reddit:goodies": {"and": 1}, "goodies:and": {"free": 1}, "and:free": {"stickers": 1}, "the:nominees": {"have": 1}, "nominees:have": {"been": 1}, "have:been": {"tabulated": 1, "published": 1}, "been:tabulated": {"the": 1}, "tabulated:the": {"final": 1}, "final:ballots": {"have": 1}, "ballots:have": {"been": 1}, "been:published": {"and": 1}, "published:and": {"it": 1}, "and:it": {"is": 1}, "for:you": {"to": 1, "a": 1}, "than:two": {"weeks": 1}, "two:weeks": {"to": 1}, "weeks:to": {"grmd": 1}, "to:grmd": {"it": 1}, "grmd:it": {"is": 1}, "for:qr": {"codes": 1}, "are:too": {"tired": 1}, "too:tired": {"to": 1}, "tired:to": {"make": 1}, "to:make": {"a": 1}, "make:a": {"blog": 1}, "a:blog": {"post": 1}, "simple:pleasures": {"condiments": 1}, "pleasures:condiments": {"star": 1}, "condiments:star": {"wars": 1}, "star:wars": {"art": 1}, "wars:art": {"prints": 1}, "art:prints": {"awesome": 1}, "prints:awesome": {"smells": 1}, "awesome:smells": {"and": 1}, "smells:and": {"plushies": 1}, "and:plushies": {"six": 1}, "plushies:six": {"new": 1}, "exchanges:on": {"redditgifts": 1}, "is:reddit": {"results": 1}, "reddit:results": {"are": 1}, "results:are": {"in": 1}, "yeah:we": {"had": 1}, "we:had": {"our": 1}, "had:our": {"gmail": 1}, "our:gmail": {"account": 1}, "gmail:account": {"broken": 1}, "account:broken": {"into": 1}, "of:winners": {"coming": 1}, "winners:coming": {"soon": 1}, "is:doubling": {"the": 1}, "doubling:the": {"size": 1}, "of:its": {"programming": 1}, "its:programming": {"team": 1}, "announcing:rabout": {"and": 1}, "rabout:and": {"the": 1}, "reddit:postcards": {"gallery": 1}, "because:you": {"deserve": 1}, "you:deserve": {"a": 1}, "deserve:a": {"second": 1}, "a:second": {"christmas": 1}, "richard:stallman": {"answers": 1, "ama": 1}, "stallman:answers": {"your": 1}, "your:top": {"questions": 4}, "have:your": {"ears": 1}, "your:ears": {"been": 1}, "ears:been": {"assaulted": 1}, "been:assaulted": {"by": 1}, "assaulted:by": {"an": 1}, "by:an": {"ad": 1}, "reddit:sorry": {"about": 1}, "sorry:about": {"that": 1}, "welcome:dante": {"brian": 1}, "dante:brian": {"kaela": 1}, "brian:kaela": {"fish": 1}, "kaela:fish": {"and": 1}, "fish:and": {"david": 1}, "today:redditgifts": {"announces": 2}, "redditgifts:announces": {"its": 1, "reddit": 1}, "announces:its": {"first": 1}, "its:first": {"ever": 1}, "first:ever": {"individual": 1}, "ever:individual": {"reddit": 1}, "individual:reddit": {"gift": 1}, "reddit:gift": {"exchange": 1}, "gift:exchange": {"for": 1}, "exchange:for": {"rbooks": 1}, "meet:us": {"at": 1}, "oh:one": {"more": 1}, "one:more": {"thing": 1}, "grow:a": {"college": 3}, "a:college": {"subreddit": 3}, "college:subreddit": {"competition": 3}, "subreddit:competition": {"results": 1}, "felicia:day": {"answers": 1, "ask": 1, "asks": 1}, "day:answers": {"your": 1}, "actress:producer": {"gamer": 1}, "producer:gamer": {"felicia": 1}, "gamer:felicia": {"day": 1}, "day:ask": {"her": 1}, "ask:her": {"anything": 1}, "her:anything": {"reddit": 1}, "max:brooks": {"author": 1, "ask": 1}, "brooks:author": {"of": 1}, "author:of": {"zombie": 1}, "of:zombie": {"survival": 1}, "zombie:survival": {"guide": 2}, "survival:guide": {"and": 1, "author": 1}, "guide:and": {"world": 1}, "and:world": {"war": 1}, "world:war": {"z": 2}, "war:z": {"answers": 1, "zombie": 1}, "z:answers": {"your": 1}, "top:questions": {"video": 1}, "questions:video": {"interview": 2}, "you:asked": {"we": 1, "directrelief": 1}, "asked:we": {"delivered": 1}, "we:delivered": {"orangered": 1}, "delivered:orangered": {"and": 1}, "orangered:and": {"periwinkle": 1}, "and:periwinkle": {"shirts": 1}, "periwinkle:shirts": {"for": 1}, "shirts:for": {"charity": 1}, "welcome:kelly": {"gary": 1}, "back:to": {"school": 1}, "to:school": {"college": 1}, "school:college": {"reddit": 1}, "college:reddit": {"meetup": 1}, "day:decorate": {"your": 1}, "decorate:your": {"dorm": 1}, "your:dorm": {"send": 1}, "dorm:send": {"teachers": 1}, "send:teachers": {"supplies": 1}, "teachers:supplies": {"and": 1}, "supplies:and": {"new": 1}, "and:new": {"gift": 1}, "new:gift": {"exchanges": 1}, "fun:in": {"the": 1}, "livestream:black": {"friday": 1}, "friday:show": {"things": 1}, "show:things": {"for": 1}, "things:for": {"which": 1}, "for:which": {"we": 1}, "which:we": {"are": 1}, "q:what": {"is": 1}, "is:hooded": {"pink": 1}, "hooded:pink": {"sketchy": 1}, "who:do": {"you": 1}, "do:you": {"nominate": 1}, "reddit:awards": {"we": 1}, "awards:we": {"will": 1}, "we:will": {"have": 1}, "will:have": {"a": 1}, "a:runoff": {"of": 1}, "runoff:of": {"the": 1}, "the:finalists": {"next": 1}, "finalists:next": {"week": 1}, "ted:curator": {"chris": 1, "redditor": 1}, "curator:chris": {"anderson": 1}, "chris:anderson": {"answers": 1, "ted": 1}, "anderson:answers": {"your": 1}, "z:zombie": {"survival": 1}, "guide:author": {"max": 1}, "author:max": {"brooks": 1}, "brooks:ask": {"him": 1}, "ask:him": {"anything": 4}, "announces:reddit": {"trick": 1}, "reddit:trick": {"or": 1}, "trick:or": {"treat": 1}, "or:treat": {"exchange": 1}, "treat:exchange": {"meetup": 1}, "exchange:meetup": {"day": 1}, "day:and": {"costume": 1, "january": 1}, "and:costume": {"contest": 1}, "is:happening": {"on": 1}, "happening:on": {"saturday": 1}, "blogreddit:how": {"to": 1}, "to:tell": {"us": 1}, "tell:us": {"about": 1}, "us:about": {"an": 1}, "about:an": {"exploit": 1}, "an:exploit": {"you": 1}, "exploit:you": {"have": 1}, "you:have": {"found": 1}, "have:found": {"and": 1}, "found:and": {"claim": 1}, "and:claim": {"your": 1}, "claim:your": {"white": 1}, "your:white": {"hat": 1}, "are:busy": {"so": 1}, "busy:so": {"tldrreddit": 1}, "so:tldrreddit": {"is": 1}, "tldrreddit:is": {"for": 1}, "is:for": {"you": 1}, "you:a": {"daily": 1}, "a:daily": {"recap": 1}, "daily:recap": {"of": 1}, "recap:of": {"the": 1}, "haiti:one": {"week": 1}, "welcome:neil": {"williams": 1}, "neil:williams": {"aka": 1}, "williams:aka": {"spladug": 1}, "a:nifty": {"community": 1}, "nifty:community": {"project": 1}, "community:project": {"that": 1}, "project:that": {"deserves": 1}, "that:deserves": {"some": 1}, "deserves:some": {"highlighting": 1}, "some:highlighting": {"radio": 1}, "highlighting:radio": {"reddit": 1}, "radio:reddit": {"the": 1}, "reddit:the": {"earworm": 1}, "the:earworm": {"of": 1}, "earworm:of": {"the": 1}, "the:hive": {"mind": 1}, "hive:mind": {"they": 1}, "mind:they": {"are": 1}, "they:are": {"still": 1}, "are:still": {"working": 1}, "still:working": {"on": 1}, "working:on": {"the": 1}, "now:available": {"in": 1}, "available:in": {"kazoo": 1}, "in:kazoo": {"form": 1}, "a:shoutout": {"to": 1}, "shoutout:to": {"the": 1}, "for:haiti": {"growing": 1}, "haiti:growing": {"we": 1}, "growing:we": {"figure": 1}, "we:figure": {"it": 1}, "figure:it": {"is": 1}, "time:we": {"did": 1, "just": 1}, "did:an": {"ask": 1}, "an:ask": {"directrelief": 1}, "ask:directrelief": {"anything": 1}, "almost:halloween": {"and": 1}, "halloween:and": {"the": 1}, "the:subreddits": {"are": 1}, "subreddits:are": {"already": 1}, "are:already": {"dressing": 1}, "already:dressing": {"up": 1}, "dressing:up": {"here": 1}, "up:here": {"are": 1}, "here:are": {"a": 1}, "few:of": {"your": 1}, "of:your": {"favorite": 1}, "your:favorite": {"new": 1}, "favorite:new": {"community": 1}, "new:community": {"stylings": 1}, "welcome:lia": {"and": 1}, "lia:and": {"alex": 1}, "new:award": {"for": 1}, "award:for": {"logo": 1}, "for:logo": {"contributors": 1}, "i:made": {"some": 1}, "made:some": {"graphs": 1}, "some:graphs": {"oh": 1}, "graphs:oh": {"and": 1}, "oh:and": {"some": 1}, "and:some": {"guy": 1}, "some:guy": {"wants": 1}, "guy:wants": {"to": 1}, "do:a": {"thing": 1}, "ask:comic": {"con": 1}, "comic:con": {"celebrities": 1}, "con:celebrities": {"anything": 1}, "day:asks": {"a": 1}, "asks:a": {"question": 1}, "a:question": {"to": 1}, "question:to": {"reddit": 1}, "be:redditgifts": {"first": 1}, "redditgifts:first": {"engineer": 1}, "record:setting": {"amount": 1}, "setting:amount": {"of": 1}, "amount:of": {"clandestine": 1}, "of:clandestine": {"holiday": 1}, "clandestine:holiday": {"cheer": 1}, "holiday:cheer": {"and": 1}, "cheer:and": {"a": 1}, "few:live": {"lobsters": 1}, "intelligence:squared": {"london": 1, "collaborate": 1}, "squared:london": {"is": 1}, "london:is": {"top": 1}, "top:debating": {"forum": 1}, "debating:forum": {"and": 1}, "forum:and": {"reddit": 1}, "and:reddit": {"collaborate": 1, "present": 1}, "reddit:collaborate": {"on": 1}, "collaborate:on": {"the": 1, "a": 1}, "for:shirts": {"and": 1}, "shirts:and": {"giggles": 2}, "hiring:a": {"community": 1}, "a:community": {"manager": 1}, "community:manager": {"for": 1, "appreciation": 1}, "manager:for": {"the": 1}, "best:community": {"in": 1}, "community:in": {"the": 1}, "san:francisco": {"mayor": 2}, "francisco:mayor": {"gavin": 2}, "mayor:gavin": {"newsom": 2}, "gavin:newsom": {"now": 2}, "newsom:now": {"the": 2}, "now:the": {"democratic": 2}, "the:democratic": {"nominee": 2}, "democratic:nominee": {"for": 2}, "nominee:for": {"lieutenant": 2}, "for:lieutenant": {"gov": 2}, "lieutenant:gov": {"of": 2}, "gov:of": {"california": 2}, "of:california": {"answers": 1, "ask": 1}, "california:answers": {"your": 1}, "celebrities:at": {"comiccon": 1}, "at:comiccon": {"sit": 1}, "comiccon:sit": {"down": 1}, "sit:down": {"for": 1}, "for:quick": {"amas": 1}, "embracing:the": {"darkness": 1}, "that:down": {"time": 1}, "down:time": {"we": 1}, "we:just": {"experienced": 1}, "just:experienced": {"gave": 1}, "experienced:gave": {"us": 1}, "gave:us": {"an": 1}, "us:an": {"opportunity": 1}, "an:opportunity": {"to": 1}, "opportunity:to": {"swap": 1}, "to:swap": {"out": 1}, "swap:out": {"the": 1}, "out:the": {"broken": 1}, "the:broken": {"db": 1}, "broken:db": {"that": 1}, "db:that": {"has": 1}, "that:has": {"been": 1}, "been:the": {"source": 1}, "the:source": {"of": 1}, "source:of": {"our": 1}, "our:recent": {"sporadic": 1}, "recent:sporadic": {"downtime": 1}, "peter:norvig": {"answers": 1}, "norvig:answers": {"your": 1}, "que:el": {"de": 1}, "el:de": {"la": 1}, "de:la": {"poblaci\u00f3n": 1}, "la:poblaci\u00f3n": {"hispanalatina": 1}, "poblaci\u00f3n:hispanalatina": {"en": 1}, "hispanalatina:en": {"eeuu": 1}, "en:eeuu": {"son": 1}, "eeuu:son": {"redditors": 1}, "open:source": {"contributor": 1}, "source:contributor": {"award": 1}, "video:interview": {"sumit": 1}, "interview:sumit": {"agarwal": 1}, "sumit:agarwal": {"the": 2}, "agarwal:the": {"us": 2}, "the:us": {"deputy": 2}, "us:deputy": {"assistant": 2}, "deputy:assistant": {"secretary": 2}, "assistant:secretary": {"of": 2}, "secretary:of": {"defense": 2}, "of:defense": {"public": 2}, "defense:public": {"affairs": 2}, "ask:chris": {"anderson": 1}, "anderson:ted": {"curator": 1}, "curator:redditor": {"anything": 1}, "the:entertainment": {"mix": 1}, "entertainment:mix": {"brought": 1}, "mix:brought": {"to": 1}, "brought:to": {"you": 1}, "to:you": {"by": 1}, "you:by": {"logitech": 1}, "by:logitech": {"revue": 1}, "we:know": {"about": 1}, "about:the": {"problem": 1, "state": 1}, "the:problem": {"with": 1}, "problem:with": {"missing": 1}, "with:missing": {"items": 1}, "missing:items": {"from": 1}, "items:from": {"some": 1}, "from:some": {"profile": 1}, "some:profile": {"and": 1}, "profile:and": {"listing": 1}, "and:listing": {"pages": 1}, "listing:pages": {"and": 1}, "pages:and": {"are": 1}, "and:are": {"working": 1}, "are:working": {"to": 1}, "working:to": {"repair": 1}, "to:repair": {"it": 1}, "author:peter": {"straub": 1}, "peter:straub": {"answers": 1}, "straub:answers": {"your": 1}, "questions:and": {"discusses": 1}, "and:discusses": {"collaboration": 1}, "discusses:collaboration": {"with": 1}, "collaboration:with": {"stephen": 1}, "with:stephen": {"king": 1}, "stephen:king": {"and": 1}, "king:and": {"advice": 1}, "and:advice": {"for": 1}, "advice:for": {"young": 1}, "for:young": {"writers": 1}, "young:writers": {"video": 1}, "writers:video": {"interview": 1}, "ma:soovin": {"rooga": 1}, "soovin:rooga": {"milles": 1}, "rooga:milles": {"oleks": 1}, "milles:oleks": {"suur": 1}, "oleks:suur": {"sealiha": 1}, "wired:is": {"danger": 2}, "is:danger": {"room": 2}, "danger:room": {"team": 1, "answers": 1}, "room:team": {"is": 1}, "team:is": {"doing": 1}, "is:doing": {"a": 1}, "a:video": {"ama": 1}, "video:ama": {"next": 1}, "ama:next": {"week": 1}, "next:week": {"ask": 1}, "week:ask": {"them": 1}, "ask:them": {"about": 1}, "them:about": {"military": 1}, "about:military": {"technology": 1}, "military:technology": {"national": 1}, "technology:national": {"security": 1}, "national:security": {"anything": 1}, "security:anything": {"else": 1}, "mold:mph": {"mmph": 1}, "mph:mmph": {"mph": 1}, "call:for": {"interns": 1}, "california:ask": {"him": 1}, "him:anything": {"video": 2}, "from:aberystwyth": {"to": 1}, "aberystwyth:to": {"york": 1}, "to:york": {"update": 1}, "york:update": {"on": 1}, "the:grow": {"a": 1}, "you:going": {"to": 1}, "be:at": {"sxsw": 1}, "at:sxsw": {"and": 1}, "sxsw:and": {"a": 1}, "personal:note": {"from": 1}, "note:from": {"ketralnis": 1}, "buy:a": {"wil": 1}, "a:wil": {"wheaton": 1}, "wil:wheaton": {"autograph": 1}, "wheaton:autograph": {"attached": 1}, "autograph:attached": {"to": 1}, "attached:to": {"an": 1}, "an:ipod": {"touch": 1}, "ipod:touch": {"and": 1}, "touch:and": {"help": 1}, "help:restore": {"missing": 1}, "restore:missing": {"civil": 1}, "missing:civil": {"liberties": 1}, "public:affairs": {"for": 1}, "affairs:for": {"outreach": 1}, "for:outreach": {"and": 1}, "outreach:and": {"social": 1}, "and:social": {"media": 1}, "social:media": {"ask": 1}, "media:ask": {"him": 1}, "asked:directrelief": {"answered": 1}, "directrelief:answered": {"learn": 1}, "answered:learn": {"about": 1}, "learn:about": {"how": 1}, "about:how": {"your": 1}, "how:your": {"dollars": 1}, "your:dollars": {"are": 1}, "dollars:are": {"helping": 1}, "are:helping": {"haiti": 1}, "manager:appreciation": {"day": 1}, "appreciation:day": {"and": 1}, "and:january": {"roundup": 1}, "super:pac": {"sleuth": 1}, "pac:sleuth": {"project": 1}, "sleuth:project": {"and": 1}, "project:and": {"other": 1}, "and:other": {"collective": 1, "upcoming": 1}, "other:collective": {"research": 1}, "collective:research": {"projects": 1}, "the:shirts": {"and": 1}, "and:giggles": {"contest": 1}, "ask:former": {"simpsons": 1}, "former:simpsons": {"writerproducer": 1}, "simpsons:writerproducer": {"and": 1}, "writerproducer:and": {"author": 1}, "and:author": {"larry": 1}, "author:larry": {"doyle": 1}, "larry:doyle": {"anything": 1}, "doyle:anything": {"video": 1}, "special:redditgifts": {"for": 1}, "redditgifts:for": {"the": 1}, "the:troops": {"and": 1}, "troops:and": {"send": 1}, "and:send": {"a": 1}, "send:a": {"care": 1}, "a:care": {"package": 1}, "care:package": {"to": 1}, "package:to": {"a": 1}, "to:a": {"redditor": 1}, "a:redditor": {"in": 1}, "redditor:in": {"the": 1}, "the:armed": {"forces": 1}, "it:turns": {"out": 1}, "turns:out": {"that": 1}, "out:that": {"there": 1}, "that:there": {"are": 1}, "there:are": {"ads": 1}, "are:ads": {"that": 1}, "ads:that": {"reddit": 1}, "that:reddit": {"actually": 1}, "reddit:actually": {"likes": 1}, "actually:likes": {"let": 1}, "likes:let": {"is": 1}, "is:recognize": {"them": 1}, "room:answers": {"your": 1}, "day:update": {"reddit": 1}, "update:reddit": {"meetup": 1}, "meetup:at": {"with": 1}, "at:with": {"free": 1}, "with:free": {"booze": 1}, "blogreddit:rpython": {"hits": 1}, "rpython:hits": {"subscribers": 1}, "hits:subscribers": {"so": 1}, "subscribers:so": {"we": 1}, "so:we": {"rolled": 1}, "we:rolled": {"you": 1}, "rolled:you": {"this": 1}, "you:this": {"code": 1}, "this:code": {"revision": 1}, "ask:joe": {"lauzon": 1}, "joe:lauzon": {"ufc": 1}, "lauzon:ufc": {"fighter": 1}, "ufc:fighter": {"and": 1}, "fighter:and": {"former": 1}, "and:former": {"network": 1}, "former:network": {"admin": 1}, "network:admin": {"anything": 1}, "admin:anything": {"reddit": 1}, "neatorama:and": {"reddit": 1}, "reddit:present": {"an": 1}, "present:an": {"unusual": 1}, "an:unusual": {"talent": 1}, "unusual:talent": {"search": 1}, "talent:search": {"great": 1}, "search:great": {"talent": 1}, "great:talent": {"fantastic": 1}, "talent:fantastic": {"or": 1}, "fantastic:or": {"otherwise": 1}, "or:otherwise": {"gtfo": 1}, "gold:now": {"takes": 1}, "now:takes": {"google": 1}, "takes:google": {"checkout": 1}, "promote:ideas": {"protect": 1}, "ideas:protect": {"people": 1}, "reddit:will": {"be": 1}, "be:down": {"when": 1}, "down:when": {"this": 1}, "when:this": {"link": 1}, "this:link": {"is": 1}, "link:is": {"minutes": 1}, "is:minutes": {"old": 1}, "introducing:rredditvideos": {"collaborate": 1}, "rredditvideos:collaborate": {"and": 1}, "collaborate:and": {"discuss": 1}, "and:discuss": {"reddit": 1}, "discuss:reddit": {"interviews": 1}, "reddit:interviews": {"and": 1}, "interviews:and": {"other": 1}, "other:upcoming": {"videos": 1}, "redditor:tv": {"host": 1}, "tv:host": {"catch": 1}, "host:catch": {"it": 1}, "catch:it": {"keep": 1}, "it:keep": {"it": 1}, "keep:it": {"punkin": 1}, "it:punkin": {"chunkin": 1}, "punkin:chunkin": {"mike": 1}, "chunkin:mike": {"senese": 1}, "mike:senese": {"answers": 1}, "senese:answers": {"your": 1}, "anil:dash": {"ask": 1}, "dash:ask": {"him": 1}, "for:those": {"of": 1}, "those:of": {"you": 1}, "of:you": {"who": 1}, "you:who": {"know": 1}, "who:know": {"football": 1}, "know:football": {"is": 1}, "football:is": {"played": 1}, "is:played": {"with": 1}, "played:with": {"a": 1}, "with:a": {"round": 1}, "a:round": {"ball": 1}, "round:ball": {"reddit": 1}, "ball:reddit": {"intelligence": 1}, "reddit:intelligence": {"squared": 1}, "squared:collaborate": {"on": 1}, "a:debate": {"about": 1}, "debate:about": {"the": 1}, "the:state": {"of": 1}, "of:footballsoccer": {"today": 1}, "are:sharing": {"our": 1}, "sharing:our": {"company": 1}, "our:company": {"is": 1}, "company:is": {"core": 1}, "is:core": {"values": 1}, "core:values": {"with": 1}, "values:with": {"the": 1}, "introducing:upvoted": {"a": 1}, "a:redditorial": {"publication": 1}}